Rabbit/__init__.py
Rabbit/rabbit_mq.py
huzzyrabbit-0.0.1.dist-info/LICENSE
huzzyrabbit-0.0.1.dist-info/METADATA
huzzyrabbit-0.0.1.dist-info/WHEEL
huzzyrabbit-0.0.1.dist-info/top_level.txt
huzzyrabbit-0.0.1.dist-info/RECORD
